ocviapy/__init__.py
ocviapy-1.5.0.dist-info/licenses/LICENSE
ocviapy-1.5.0.dist-info/METADATA
ocviapy-1.5.0.dist-info/WHEEL
ocviapy-1.5.0.dist-info/top_level.txt
ocviapy-1.5.0.dist-info/RECORD
